{
  "$schema": "http://adaptivecards.io/schemas/adaptive-card.json",
  "type": "AdaptiveCard",
  "version": "1.0",
  "body": [
    {
      "type": "Image",
      "url": "https://user.oc-static.com/upload/2019/10/24/15719199766568_Capture%20d%E2%80%99e%CC%81cran%202019-10-24%20a%CC%80%2014.14.41.png",
      "size": "stretch"
    },
    {
      "type": "TextBlock",
      "spacing": "medium",
      "size": "default",
      "weight": "bolder",
      "text": "Welcome to Fly Me!",
      "wrap": true,
      "maxLines": 0
    },
    {
      "type": "TextBlock",
      "size": "default",
      "isSubtle": "true",
      "text": "I'm here to help you find your next trip !",
      "wrap": true,
      "maxLines": 0
    }
  ]
}
